Metadata-Version: 2.1
Name: choto
Version: 1.0.3
Summary: A CLI tool that summarizes news and articles.
Home-page: https://github.com/ayushsubedi/choto
Author: Ayush Subedi
Author-email: ayush.subedi@gmail.com
License: UNKNOWN
Project-URL: Bug Reports, https://github.com/ayushsubedi/choto/issues
Project-URL: Source, https://github.com/ayushsubedi/choto
Platform: UNKNOWN
Requires-Python: >=3.6, <3.9
